mitorch/models/__init__.py
mitorch/models/classifier.py
mitorch/models/efficientnet.py
mitorch/models/factory.py
mitorch/models/mobilenetv2.py
mitorch/models/mobilenetv3.py
mitorch/models/model.py
mitorch/models/resnext.py
mitorch/models/retinanet.py
mitorch/models/retinanet_lite.py
mitorch/models/seresnext.py
mitorch/models/shufflenet.py
mitorch/models/shufflenetv2.py
mitorch/models/squeezenet.py
mitorch/models/ssd_lite.py
mitorch/models/vgg.py
mitorch/models/heads/__init__.py
mitorch/models/heads/bidirectional_feature_pyramid_network.py
mitorch/models/heads/feature_pyramid_network.py
mitorch/models/heads/head.py
mitorch/models/heads/mnas_fpn.py
mitorch/models/heads/ssdlite_extra_layers.py
mitorch/models/modules/__init__.py
mitorch/models/modules/activation.py
mitorch/models/modules/addition.py
mitorch/models/modules/base.py
mitorch/models/modules/convolution.py
mitorch/models/modules/depthwise_separable_conv.py
mitorch/models/modules/focal_loss.py
mitorch/models/modules/linear.py
mitorch/models/modules/mbconv.py
mitorch/models/modules/non_max_suppression.py
mitorch/models/modules/prior_box.py
mitorch/models/modules/retina_predictor.py
mitorch/models/modules/retina_prior_box.py
mitorch/models/modules/se_block.py
mitorch/models/modules/shuffle.py
mitorch/models/modules/ssd_loss.py
mitorch/models/modules/ssd_predictor.py
mitorch_models-0.0.6.dist-info/LICENSE
mitorch_models-0.0.6.dist-info/METADATA
mitorch_models-0.0.6.dist-info/WHEEL
mitorch_models-0.0.6.dist-info/top_level.txt
mitorch_models-0.0.6.dist-info/RECORD
