Metadata-Version: 2.1
Name: mitorch-models
Version: 0.0.6
Summary: Collection of vision-related pytorch models with a focus on code readability
Home-page: https://github.com/shonohs/mitorch_models
Author: shono
Author-email: UNKNOWN
License: MIT
Platform: UNKNOWN
Classifier: Development Status :: 4 - Beta
Classifier: License :: OSI Approved :: MIT License
Classifier: Programming Language :: Python :: 3 :: Only
Classifier: Topic :: Scientific/Engineering :: Artificial Intelligence
Requires-Dist: torch (>=1.4)
